CHANGES.rst
CONTRIBUTORS
LICENSE
MANIFEST.in
README.rst
setup.py
who_dev/__init__.py
who_dev.egg-info/PKG-INFO
who_dev.egg-info/SOURCES.txt
who_dev.egg-info/dependency_links.txt
who_dev.egg-info/not-zip-safe
who_dev.egg-info/requires.txt
who_dev.egg-info/top_level.txt