Metadata-Version: 1.1
Name: who-dev
Version: 0.0.2
Summary: A developer-mode plugin for repoze.who
Home-page: https://github.com/m-martinez/who_dev
Author: UNKNOWN
Author-email: UNKNOWN
License: BSD-derived (http://www.repoze.org/LICENSE.txt)
Keywords: web application server wsgi repoze repoze.who
Platform: UNKNOWN
Classifier: Intended Audience :: Developers
Classifier: Natural Language :: English
Classifier: Operating System :: OS Independent
Classifier: Programming Language :: Python
Classifier: Programming Language :: Python :: 2.7
Classifier: Programming Language :: Python :: 3.5
Classifier: Topic :: Internet :: WWW/HTTP :: WSGI :: Middleware
